{
	"info": {
		"_postman_id": "e7db6df2-0e0a-433c-94bc-896905af435d",
		"name": "API Collection",
		"schema": "https://schema.getpostman.com/json/collection/v2.1.0/collection.json",
		"_exporter_id": "25899181"
	},
	"item": [
		{
			"name": "test result Petstore",
			"event": [
				{
					"listen": "test",
					"script": {
						"exec": [
							"pm.test(\"Status code should be 200\", function () {\r",
							"pm.test(\"Status code name should have an OK string\", function () {\r",
							"    pm.response.to.have.status(\"OK\");\r",
							"});\r",
							"    pm.response.to.have.status(200);\r",
							"});\r",
							"\r",
							""
						],
						"type": "text/javascript"
					}
				}
			],
			"protocolProfileBehavior": {
				"disableBodyPruning": true
			},
			"request": {
				"method": "GET",
				"header": [],
				"body": {
					"mode": "raw",
					"raw": "",
					"options": {
						"raw": {
							"language": "json"
						}
					}
				},
				"url": {
					"raw": "{{baseUrl}}/swagger.json",
					"host": [
						"{{baseUrl}}"
					],
					"path": [
						"swagger.json"
					],
					"query": [
						{
							"key": "id",
							"value": "3",
							"disabled": true
						}
					]
				}
			},
			"response": []
		}
	]
}